[
    {
        "name": "Ronin",
        "date": 1648512000,
        "inUSD": 622000000,
        "assets": "173,600 WETH and 25.5 million USDC",
        "reasonShort": "Compromised private keys",
        "reasonLong": "The attacker used \u201chacked private keys\u201d to execute the exploit, per the team\u2019s report, and thus was able to forge transactions to claim the funds.",
        "audited": "Yes",
        "refunded": "Yes",
        "category": "Bridge",
        "url1": "https://twitter.com/Ronin_Network/status/1508828719711879168",
        "url2": "https://roninblockchain.substack.com/p/community-alert-ronin-validators?s=w",
        "url3": "https://decrypt.co/96322/hacker-622-million-axie-infinity-ronin-ethereum",
        "desc": "The Ronin bridge has been exploited for 173,600 Ethereum and 25.5M USDC. The Ronin bridge and Katana Dex have been halted.",
        "chain": "Ethereum",
        "hackerWallet1": "https://etherscan.io/address/0x098b716b8aaf21512996dc57eb0615e2383e2f96",
        "hackerWallet2": "",
        "hackerWallet3": "",
        "party": "Sky Mavis",
        "type": "Hack",
        "status": "Still Alive",
        "rank": 1,
        "updated": "2023-01-01 19:16:17"
    },
    {
        "name": "Poly Network",
        "date": 1628553600,
        "inUSD": 611000000,
        "assets": "173,600 WETH and 25.5 million USDC",
        "reasonShort": "Contract bug",
        "reasonLong": "According to cybersecurity firm SlowMist and security researcher Kelvin Fichter, the hack was made possible by a mismanagement of the access rights between two important Poly smart contract. The first one is EthCrossChainManager and the second one is EthCrossChainData.",
        "audited": "Yes",
        "refunded": "Yes",
        "category": "Bridge",
        "url1": "https://twitter.com/PolyNetwork2/status/1425073987164381196",
        "url2": "https://decrypt.co/78275/what-the-poly-network-hack-reveals-about-defi",
        "url3": "https://cointelegraph.com/news/poly-network-hacker-returns-nearly-all-funds-refuses-500k-white-hat-bounty",
        "desc": "Interoperability protocol Poly Network was hacked for over $600 million.",
        "chain": "Ethereum, BNB, Polygon",
        "hackerWallet1": "https://etherscan.io/address/0xc8a65fadf0e0ddaf421f28feab69bf6e2e589963",
        "hackerWallet2": "https://bscscan.com/address/0x0d6e286a7cfd25e0c01fee9756765d8033b32c71",
        "hackerWallet3": "https://polygonscan.com/address/0x5dc3603c9d42ff184153a8a9094a73d461663214",
        "party": "Poly Network",
        "type": "Hack",
        "status": "Still Alive",
        "rank": 2,
        "updated": "2023-01-01 19:16:17"
    },
    {
        "name": "Coincheck",
        "date": 1516924800,
        "inUSD": 534000000,
        "assets": "523 millions NEM",
        "reasonShort": "Compromised private keys",
        "reasonLong": "The stolen Coincheck assets were said to be kept in a hot wallet - a part of the exchange connected to the internet. That contrasts with a cold wallet, where funds are stored securely offline.",
        "audited": "Yes",
        "refunded": "Yes",
        "category": "CEX",
        "url1": "https://corporate.coincheck.com/2018/01/26/29.html",
        "url2": "https://www.bbc.com/news/world-asia-42845505",
        "url3": "https://coincheck.blog/4671",
        "desc": "Coincheck is one of Japan's largest digital currency exchange.",
        "chain": "NEM",
        "hackerWallet1": "",
        "hackerWallet2": "",
        "hackerWallet3": "",
        "party": "Coincheck",
        "type": "Hack",
        "status": "Still Alive",
        "country": "Japan",
        "rank": 3,
        "updated": "2023-01-01 19:16:17"
    },
    {
        "name": "Mt. Gox",
        "date": 1391731200,
        "inUSD": 473000000,
        "assets": "844,408 BTC",
        "reasonShort": "Compromised private keys",
        "reasonLong": "Mt. Gox released a statement saying, The company believes there is a high possibility that the bitcoins were stolen, blamed hackers, and began a search for the missing bitcoins.",
        "audited": "No",
        "refunded": "Partially",
        "category": "CEX",
        "url1": "https://en.wikipedia.org/wiki/Mt._Gox",
        "url2": "https://www.investopedia.com/terms/m/mt-gox.asp",
        "url3": "",
        "desc": "Mt. Gox was a cryptocurrency exchange that operated between 2010 and 2014.",
        "chain": "BTC",
        "hackerWallet1": "",
        "hackerWallet2": "",
        "hackerWallet3": "",
        "party": "Mt. Gox",
        "type": "Hack",
        "status": "Dead",
        "country": "Japan",
        "rank": 4,
        "updated": "2023-01-01 19:16:17"
    },
    {
        "name": "Wormhole",
        "date": 1643760000,
        "inUSD": 325000000,
        "assets": "120,000 WETH",
        "reasonShort": "Contract bug",
        "reasonLong": "An attacker exploited a signature verification vulnerability in the Wormhole network to mint 120k Wormhole-wrapped Ether on Solana.",
        "audited": "No",
        "refunded": "Yes",
        "category": "Bridge",
        "url1": "https://wormholecrypto.medium.com/wormhole-incident-report-02-02-22-ad9b8f21eec6",
        "url2": "https://decrypt.co/91899/hacker-steals-320-million-solana-ethereum-bridge-wormhole",
        "url3": "",
        "desc": "Interoperability protocol powering the seamless transfer of value and information across 14 high value chains with just one integration",
        "chain": "Solana",
        "hackerWallet1": "",
        "hackerWallet2": "",
        "hackerWallet3": "",
        "party": "Jump Trading",
        "type": "Hack",
        "status": "Still Alive",
        "rank": 5,
        "updated": "2023-01-01 19:16:17"
    },
    {
        "name": "KuCoin",
        "date": 1601078400,
        "inUSD": 281000000,
        "assets": "1,008 BTC, 11,543 ETH, 19,834,042 USDT-ETH, 18,495,798 XRP, 26,733 LTC, 999,160 USDT, $147M worth of ERC-20 tokens, $87M of Stellar tokens",
        "reasonShort": "Compromised private keys",
        "reasonLong": "We found that KuCoin encountered a complex APT attack in September 2020. The attacker was lurking for a long time, and this attack severely damaged our internal network, allowing the attacker to bypass the security system of KuCoin and obtain the private keys of a few hot wallets.",
        "audited": "No",
        "refunded": "Yes",
        "category": "CEX",
        "url1": "https://www.kucoin.com/news/en-kucoin-security-incident-update",
        "url2": "https://blog.chainalysis.com/reports/kucoin-hack-2020-defi-uniswap/",
        "url3": "",
        "desc": "KuCoin is a large cryptocurrency exchange offering the ability to buy, sell, and trade cryptocurrencies.",
        "chain": "",
        "hackerWallet1": "",
        "hackerWallet2": "",
        "hackerWallet3": "",
        "party": "KuCoin",
        "type": "Hack",
        "status": "Still Alive",
        "country": "Seychelles",
        "rank": 6,
        "updated": "2023-01-01 19:16:17"
    },
    {
        "name": "BitMart",
        "date": 1638576000,
        "inUSD": 196000000,
        "assets": "196 million worth Ethereum",
        "reasonShort": "Compromised private keys",
        "reasonLong": "Large-scale security breach related to one of our ETH hot wallets and one of our BSC hot wallets.",
        "audited": "No",
        "refunded": "Unknown",
        "category": "CEX",
        "url1": "https://twitter.com/sheldonbitmart/status/1467316252855226368",
        "url2": "https://www.coindesk.com/tech/2021/12/06/bitmart-ceo-says-stolen-private-key-behind-196m-hack/",
        "url3": "https://coinmarketcap.com/alexandria/article/bitmart-hack-one-of-the-most-recent-crypto-hacks",
        "desc": "BitMart is a global cryptocurrency exchange that allows users in 180+ countries to buy and sell over 1,000 digital currencies and tokens.",
        "chain": "Ethereum, BSC",
        "hackerWallet1": "",
        "hackerWallet2": "",
        "hackerWallet3": "",
        "party": "BitMart",
        "type": "Hack",
        "status": "Still Alive",
        "country": "Cayman islands",
        "rank": 7,
        "updated": "2023-01-01 19:16:17"
    },
    {
        "name": "Nomad",
        "date": 1659312000,
        "inUSD": 186000000,
        "assets": "$186 million in Ethereum",
        "reasonShort": "Contract bug",
        "reasonLong": "An implementation bug caused the Replica contract to fail to authenticate messages properly. This issue allowed any message to be forged as long as it had not already been processed.",
        "audited": "No",
        "refunded": "No",
        "category": "Bridge",
        "url1": "https://medium.com/nomad-xyz-blog/the-road-to-recovery-6abe5eec8ff1",
        "url2": "https://decrypt.co/106459/crypto-bridge-nomad-exploited-190m-frenzied-free-for-all",
        "url3": "https://www.coindesk.com/business/2022/08/03/hackers-send-back-9m-to-nomad-bridge-after-190m-exploit/",
        "desc": "Nomad is an interoperability protocol for generalized message passing. We leverage an optimistic mechanism.",
        "chain": "Ethereum",
        "hackerWallet1": "",
        "hackerWallet2": "",
        "hackerWallet3": "",
        "party": "Nomad",
        "type": "Hack",
        "status": "Dead",
        "rank": 8,
        "updated": "2023-01-01 19:16:17"
    },
    {
        "name": "Beanstalk",
        "date": 1650240000,
        "inUSD": 182000000,
        "assets": "$182 million in Ethereum",
        "reasonShort": "Flash loan attack",
        "reasonLong": "The hacker used a flash loan, which allows people to borrow an asset to make a quick trade and then repay the asset\u2014all in just one complex transaction that involves multiple protocols.",
        "audited": "No",
        "refunded": "No",
        "category": "Algo-Stable",
        "url1": "https://twitter.com/BeanstalkFarms/status/1515747114894065664",
        "url2": "https://halborn.com/explained-the-beanstalk-hack-april-2022/",
        "url3": "https://decrypt.co/98118/ethereum-defi-protocol-beanstalk-hacked-182-million-what-you-need-know",
        "desc": "Beanstalk is known for its algorithmic stablecoin, BEAN, which is supposed to be worth $1.",
        "chain": "Ethereum",
        "hackerWallet1": "",
        "hackerWallet2": "",
        "hackerWallet3": "",
        "party": "Beanstalk",
        "type": "Hack",
        "status": "Resurrected",
        "rank": 9,
        "updated": "2023-01-01 19:16:17"
    },
    {
        "name": "Wintermute",
        "date": 1663663624,
        "inUSD": 160000000,
        "assets": "160,000 million dollar",
        "reasonShort": "Unknown",
        "reasonLong": "Gaevoy added that the company is still treating the hack as a white hat event and asked the hacker to get in touch.",
        "audited": "No",
        "refunded": "No",
        "category": "Crypto Market Maker",
        "url1": "https://twitter.com/EvgenyGaevoy/status/1572134273875951617",
        "url2": "https://www.coindesk.com/business/2022/09/20/crypto-market-maker-wintermute-hacked-for-160m-says-ceo/",
        "url3": "",
        "desc": "Crypto Market Maker",
        "chain": "Ethereum",
        "hackerWallet1": "",
        "hackerWallet2": "",
        "hackerWallet3": "",
        "party": "Wintermute",
        "type": "Hack",
        "status": "Still Alive",
        "country": "",
        "rank": 10,
        "updated": "2023-01-01 19:16:17"
    },
    {
        "name": "Compound",
        "date": 1633219200,
        "inUSD": 147000000,
        "assets": "202,472 COMP",
        "reasonShort": "Contract bug",
        "reasonLong": "A week ago, Compound founder Robert Leshner called a bug in his lending protocol\u2019s smart contract a moral dilemma.",
        "audited": "No",
        "refunded": "Partially",
        "category": "Lending",
        "url1": "https://twitter.com/bantg/status/1444643482216304641",
        "url2": "https://decrypt.co/82499/compound-exploit-drains-21m-from-lending-protocol",
        "url3": "",
        "desc": "Compound is an algorithmic, autonomous interest rate protocol built for developers, to unlock a universe of open financial applications.",
        "chain": "Ethereum",
        "hackerWallet1": "",
        "hackerWallet2": "",
        "hackerWallet3": "",
        "party": "Compound",
        "type": "Hack",
        "status": "Still Alive",
        "rank": 11,
        "updated": "2023-01-01 19:16:17"
    },
    {
        "name": "BitGrail",
        "date": 1640044800,
        "inUSD": 146000000,
        "assets": "230,000 BitGrail users lost funds",
        "reasonShort": "Exit Scam",
        "reasonLong": "A man who ran the now-bankrupt BitGrail exchange may have been behind a series of hacks that stole \u20ac120 million.",
        "audited": "No",
        "refunded": "No",
        "category": "CEX",
        "url1": "https://www.reuters.com/article/italy-cyber-cryptocurrency/italian-police-accuse-cryptocurrency-exchange-boss-of-huge-fraud-idUSL8N2J127X",
        "url2": "https://www.coindesk.com/markets/2020/12/21/bitgrail-operator-may-have-hacked-own-exchange-to-steal-120m-police-allege/",
        "url3": "",
        "desc": "Italian CEX.",
        "chain": "Nano",
        "hackerWallet1": "",
        "hackerWallet2": "",
        "hackerWallet3": "",
        "party": "BitGrail",
        "type": "Exit Scam",
        "status": "Dead",
        "country": "Italy",
        "rank": 12,
        "updated": "2023-01-01 19:16:17"
    },
    {
        "name": "Vulcan Forged",
        "date": 1639353600,
        "inUSD": 140000000,
        "assets": "4.5 million of Vulcan Forged native PYR tokens",
        "reasonShort": "Compromised private keys",
        "reasonLong": "A hacker exploited the Polygon-based platform to get hold of the private keys to 96 crypto wallets.",
        "audited": "No",
        "refunded": "Yes",
        "category": "Gaming",
        "url1": "https://decrypt.co/88177/hacker-steals-140-million-polygon-gaming-platform-nft-marketplace-vulcan-forged",
        "url2": "",
        "url3": "",
        "desc": "A play-to-earn platform on Polygon.",
        "chain": "Polygon",
        "hackerWallet1": "",
        "hackerWallet2": "",
        "hackerWallet3": "",
        "party": "Vulcan Forged",
        "type": "Hack",
        "status": "Still Alive",
        "rank": 13,
        "updated": "2023-01-01 19:16:17"
    },
    {
        "name": "BXH",
        "date": 1635552000,
        "inUSD": 139000000,
        "assets": "139,000 million in BNB",
        "reasonShort": "Compromised private keys",
        "reasonLong": "Leaked administrator key.",
        "audited": "No",
        "refunded": "Yes",
        "category": "CEX",
        "url1": "https://twitter.com/BXH_Blockchain/status/1454366374353010695",
        "url2": "https://www.coindesk.com/tech/2021/11/01/139m-bxh-exchange-hack-was-the-result-of-leaked-admin-key/",
        "url3": "",
        "desc": "",
        "chain": "BNB",
        "hackerWallet1": "",
        "hackerWallet2": "",
        "hackerWallet3": "",
        "party": "BXH",
        "type": "Hack",
        "status": "Still Alive",
        "country": "China",
        "rank": 14,
        "updated": "2023-01-01 19:16:17"
    },
    {
        "name": "Cream Finance",
        "date": 1635292800,
        "inUSD": 130000000,
        "assets": "139,000 million in BNB",
        "reasonShort": "Flash loan attack",
        "reasonLong": "flash loan",
        "audited": "No",
        "refunded": "No",
        "category": "Lending",
        "url1": "https://twitter.com/CreamdotFinance/status/1453377073699983366",
        "url2": "https://www.coindesk.com/business/2021/10/27/cream-finance-exploited-in-flash-loan-attack-worth-over-100m/",
        "url3": "",
        "desc": "",
        "chain": "Ethereum",
        "hackerWallet1": "",
        "hackerWallet2": "",
        "hackerWallet3": "",
        "party": "Cream Finance",
        "type": "Hack",
        "status": "Still Alive",
        "country": "",
        "rank": 15,
        "updated": "2023-01-01 19:16:17"
    },
    {
        "name": "BadgerDAO",
        "date": 1638403200,
        "inUSD": 121168753,
        "assets": "121,000 million dollar",
        "reasonShort": "Front-end attack",
        "reasonLong": "Investigators Believe Unauthorized API Key Allowed Malicious Snippet to Set User Web3 Permission to Attacker Wallet.",
        "audited": "No",
        "refunded": "Partially",
        "category": "Yield Aggregator",
        "url1": "https://badger.com/technical-post-mortem",
        "url2": "https://www.coindesk.com/business/2021/12/10/badgerdao-reveals-details-of-how-it-was-hacked-for-120m/",
        "url3": "",
        "desc": "BadgerDAO dedicated to building products and infrastructure to bring Bitcoin to DeFi.",
        "chain": "Ethereum",
        "hackerWallet1": "",
        "hackerWallet2": "",
        "hackerWallet3": "",
        "party": "BadgerDAO",
        "type": "Hack",
        "status": "Still Alive",
        "country": "",
        "rank": 16,
        "updated": "2023-01-01 19:16:17"
    },
    {
        "name": "Horizon",
        "date": 1655942400,
        "inUSD": 100000000,
        "assets": "100,000 million in BUSD, USDC, ETH, and WBTC",
        "reasonShort": "Compromised private keys",
        "reasonLong": "Funds were stolen from the Ethereum side of the bridge.",
        "audited": "No",
        "refunded": "No",
        "category": "Bridge",
        "url1": "https://twitter.com/harmonyprotocol/status/1540380101308608512",
        "url2": "https://medium.com/harmony-one/harmonys-horizon-bridge-hack-1e8d283b6d66",
        "url3": "https://twitter.com/stse/status/1540896632278900737",
        "desc": "",
        "chain": "Ethereum",
        "hackerWallet1": "https://etherscan.io/address/0x0d043128146654c7683fbf30ac98d7b2285ded00",
        "hackerWallet2": "",
        "hackerWallet3": "",
        "party": "Harmony",
        "type": "Hack",
        "status": "Still Alive",
        "country": "",
        "rank": 17,
        "updated": "2023-01-01 19:16:17"
    },
    {
        "name": "Qubit",
        "date": 1643328000,
        "inUSD": 80000000,
        "assets": "206,809 Binance Coin",
        "reasonShort": "Contract bug",
        "reasonLong": "Hackers stole 206,809 Binance Coin, roughly $80 million, from Qubit\u2019s QBridge protocol, making it the seventh largest DeFi hack ever.",
        "audited": "No",
        "refunded": "No",
        "category": "Lending",
        "url1": "https://blockworks.co/defi-protocol-qubit-finance-loses-80m-in-hack/",
        "url2": "https://twitter.com/QubitFin/status/1486984216072318977",
        "url3": "",
        "desc": "Lend to Ascend, Borrow for Tomorrow. Revolutionary Lending Platfrom.",
        "chain": "Ethereum",
        "hackerWallet1": "",
        "hackerWallet2": "",
        "hackerWallet3": "",
        "party": "Qubit",
        "type": "Hack",
        "status": "Still Alive",
        "country": "",
        "rank": 18,
        "updated": "2023-01-01 19:16:17"
    }
]